apecode/__init__.py
apecode/cli.py
apecode-0.0.1.dist-info/METADATA
apecode-0.0.1.dist-info/WHEEL
apecode-0.0.1.dist-info/entry_points.txt
apecode-0.0.1.dist-info/licenses/LICENSE
apecode-0.0.1.dist-info/RECORD
