Metadata-Version: 2.4
Name: apecode
Version: 0.0.1
Summary: A terminal code agent powered by AI
Author: ApeCode Team
License: MIT
License-File: LICENSE
Keywords: agent,ai,cli,code,terminal
Classifier: Development Status :: 2 - Pre-Alpha
Classifier: Intended Audience :: Developers
Classifier: License :: OSI Approved :: MIT License
Classifier: Programming Language :: Python :: 3
Classifier: Programming Language :: Python :: 3.13
Requires-Python: >=3.13
